tf_keras/__init__.py
tf_keras_nightly-0.0.0.dist-info/METADATA
tf_keras_nightly-0.0.0.dist-info/WHEEL
tf_keras_nightly-0.0.0.dist-info/top_level.txt
tf_keras_nightly-0.0.0.dist-info/RECORD
