Metadata-Version: 2.1
Name: tf-keras-nightly
Version: 0.0.0
Summary: TensorFlow Keras (nightly release).
Home-page: https://github.com/keras-team/tf-keras
Author: Keras team
Author-email: keras-users@googlegroups.com
License: Apache License 2.0
Classifier: Development Status :: 4 - Beta
Classifier: Programming Language :: Python :: 3
Classifier: Programming Language :: Python :: 3.8
Classifier: Programming Language :: Python :: 3.9
Classifier: Programming Language :: Python :: 3.10
Classifier: Programming Language :: Python :: 3.11
Classifier: Programming Language :: Python :: 3 :: Only
Classifier: Operating System :: Unix
Classifier: Operating System :: MacOS
Classifier: Intended Audience :: Science/Research
Classifier: Topic :: Scientific/Engineering
Classifier: Topic :: Software Development
Requires-Python: >=3.8
